kylie/__init__.py
kylie/kylie.py
kylie-0.3.1.dist-info/DESCRIPTION.rst
kylie-0.3.1.dist-info/METADATA
kylie-0.3.1.dist-info/metadata.json
kylie-0.3.1.dist-info/pbr.json
kylie-0.3.1.dist-info/RECORD
kylie-0.3.1.dist-info/top_level.txt
kylie-0.3.1.dist-info/WHEEL
