Metadata-Version: 2.0
Name: kylie
Version: 0.3.1
Summary: Kylie provides mappings between JSON data structures and Python objects.
Home-page: https://github.com/judy2k/kylie
Author: Mark Smith
Author-email: mark.smith@practicalpoetry.co.uk
License: BSD
Keywords: kylie
Platform: UNKNOWN
Classifier: Development Status :: 4 - Beta
Classifier: Intended Audience :: Developers
Classifier: License :: OSI Approved :: BSD License
Classifier: Natural Language :: English
Classifier: Programming Language :: Python :: 2
Classifier: Programming Language :: Python :: 2.6
Classifier: Programming Language :: Python :: 2.7
Classifier: Programming Language :: Python :: 3
Classifier: Programming Language :: Python :: 3.3
Classifier: Programming Language :: Python :: 3.4
